nimbus_gateway/__init__.py
nimbus_gateway/aliyun/__init__.py
nimbus_gateway/aliyun/api/__init__.py
nimbus_gateway/aliyun/api/gateway/__init__.py
nimbus_gateway/aliyun/api/gateway/sdk/__init__.py
nimbus_gateway/aliyun/api/gateway/sdk/client.py
nimbus_gateway/aliyun/api/gateway/sdk/constant.py
nimbus_gateway/aliyun/api/gateway/sdk/req.py
nimbus_gateway/aliyun/api/gateway/sdk/utils/__init__.py
nimbus_gateway/aliyun/api/gateway/sdk/utils/date_util.py
nimbus_gateway/aliyun/api/gateway/sdk/utils/message.py
nimbus_gateway/aliyun/api/gateway/sdk/utils/signature.py
nimbus_gateway-1.1.4.dist-info/LICENSE.md
nimbus_gateway-1.1.4.dist-info/METADATA
nimbus_gateway-1.1.4.dist-info/WHEEL
nimbus_gateway-1.1.4.dist-info/top_level.txt
nimbus_gateway-1.1.4.dist-info/RECORD
